numpydantic-1.7.0.dist-info/METADATA
numpydantic-1.7.0.dist-info/WHEEL
numpydantic-1.7.0.dist-info/entry_points.txt
numpydantic-1.7.0.dist-info/licenses/LICENSE
numpydantic/.DS_Store
numpydantic/__init__.py
numpydantic/dtype.py
numpydantic/exceptions.py
numpydantic/interface/__init__.py
numpydantic/interface/dask.py
numpydantic/interface/hdf5.py
numpydantic/interface/interface.py
numpydantic/interface/numpy.py
numpydantic/interface/video.py
numpydantic/interface/xarray.py
numpydantic/interface/zarr.py
numpydantic/maps.py
numpydantic/meta.py
numpydantic/ndarray.py
numpydantic/ndarray.pyi
numpydantic/py.typed
numpydantic/schema.py
numpydantic/serialization.py
numpydantic/testing/__init__.py
numpydantic/testing/cases.py
numpydantic/testing/helpers.py
numpydantic/testing/interfaces.py
numpydantic/types.py
numpydantic/validation/__init__.py
numpydantic/validation/dtype.py
numpydantic/validation/shape.py
numpydantic/vendor/.DS_Store
numpydantic/vendor/__init__.py
numpydantic/vendor/nptyping/.DS_Store
numpydantic/vendor/nptyping/__init__.py
numpydantic/vendor/nptyping/assert_isinstance.py
numpydantic/vendor/nptyping/base_meta_classes.py
numpydantic/vendor/nptyping/error.py
numpydantic/vendor/nptyping/ndarray.py
numpydantic/vendor/nptyping/ndarray.pyi
numpydantic/vendor/nptyping/nptyping_type.py
numpydantic/vendor/nptyping/package_info.py
numpydantic/vendor/nptyping/pandas_/__init__.py
numpydantic/vendor/nptyping/pandas_/dataframe.py
numpydantic/vendor/nptyping/pandas_/dataframe.pyi
numpydantic/vendor/nptyping/pandas_/typing_.py
numpydantic/vendor/nptyping/py.typed
numpydantic/vendor/nptyping/recarray.py
numpydantic/vendor/nptyping/recarray.pyi
numpydantic/vendor/nptyping/shape.py
numpydantic/vendor/nptyping/shape.pyi
numpydantic/vendor/nptyping/shape_expression.py
numpydantic/vendor/nptyping/structure.py
numpydantic/vendor/nptyping/structure.pyi
numpydantic/vendor/nptyping/structure_expression.py
numpydantic/vendor/nptyping/typing_.py
numpydantic-1.7.0.dist-info/RECORD
