Metadata-Version: 2.1
Name: numpydantic
Version: 1.7.0
Summary: Type and shape validation and serialization for arbitrary array types in pydantic models
Keywords: arrays,validation,serialization,numpy,pydantic
Author-Email: sneakers-the-rat <sneakers-the-rat@protonmail.com>
License: MIT
Classifier: Framework :: Pydantic
Classifier: Framework :: Pydantic :: 2
Classifier: Development Status :: 5 - Production/Stable
Classifier: Intended Audience :: Developers
Classifier: Intended Audience :: Science/Research
Classifier: License :: OSI Approved :: MIT License
Classifier: Natural Language :: English
Classifier: Operating System :: MacOS
Classifier: Operating System :: Microsoft :: Windows
Classifier: Operating System :: POSIX :: Linux
Classifier: Programming Language :: Python :: 3
Classifier: Programming Language :: Python :: 3.9
Classifier: Programming Language :: Python :: 3.10
Classifier: Programming Language :: Python :: 3.11
Classifier: Programming Language :: Python :: 3.12
Classifier: Topic :: File Formats :: JSON :: JSON Schema
Classifier: Topic :: Utilities
Project-URL: homepage, https://numpydantic.readthedocs.io
Project-URL: documentation, https://numpydantic.readthedocs.io
Project-URL: repository, https://github.com/p2p-ld/numpydantic
Project-URL: changelog, https://numpydantic.readthedocs.io/en/latest/changelog.html
Requires-Python: <4.0,>=3.9
Requires-Dist: pydantic>=2.7.0
Requires-Dist: numpy>=1.24.0
Requires-Dist: typing-extensions>=4.11.0; python_version < "3.11"
Provides-Extra: dask
Requires-Dist: dask>=2024.4.0; extra == "dask"
Provides-Extra: hdf5
Requires-Dist: h5py>=3.10.0; extra == "hdf5"
Provides-Extra: video
Requires-Dist: opencv-python>=4.9.0.80; extra == "video"
Provides-Extra: zarr
Requires-Dist: zarr<3.0.0,>=2.17.2; extra == "zarr"
Provides-Extra: arrays
Requires-Dist: numpydantic[dask,hdf5,video,zarr]; extra == "arrays"
Provides-Extra: tests
Requires-Dist: numpydantic[arrays]; extra == "tests"
Requires-Dist: pytest>=7.4.0; extra == "tests"
Requires-Dist: pytest-depends<2.0.0,>=1.0.1; extra == "tests"
Requires-Dist: coverage>=6.1.1; extra == "tests"
Requires-Dist: pytest-cov<5.0.0,>=4.1.0; extra == "tests"
Requires-Dist: coveralls<4.0.0,>=3.3.1; extra == "tests"
Requires-Dist: mypy>=1.17.1; extra == "tests"
Provides-Extra: docs
Requires-Dist: numpydantic[arrays]; extra == "docs"
Requires-Dist: sphinx<8.0.0,>=7.2.6; extra == "docs"
Requires-Dist: furo>=2024.1.29; extra == "docs"
Requires-Dist: myst-parser<3.0.0,>=2.0.0; extra == "docs"
Requires-Dist: autodoc-pydantic<3.0.0,>=2.0.1; extra == "docs"
Requires-Dist: sphinx-design<1.0.0,>=0.5.0; extra == "docs"
Requires-Dist: sphinxcontrib-mermaid>=0.9.2; extra == "docs"
Requires-Dist: myst-nb>=1.1.1; extra == "docs"
Requires-Dist: rich>=13.8.1; extra == "docs"
Provides-Extra: dev
Requires-Dist: numpydantic[docs,tests]; extra == "dev"
Requires-Dist: sphinx-autobuild>=2021.3.14; extra == "dev"
Requires-Dist: black>=24.1.1; extra == "dev"
Requires-Dist: ruff<1.0.0,>=0.2.0; extra == "dev"
